{
    "songkick_response": {
        "status": "ok", 
        "ageRestriction": null, 
        "displayName": "Trout Steak Revival with The Warren G. Hardings and The Railsplitters at Nectar Lounge (November 17, 2016)", 
        "popularity": 0.000198, 
        "venue": {
            "displayName": "Nectar Lounge", 
            "uri": "http://www.songkick.com/venues/11589-nectar-lounge?utm_source=32233&utm_medium=partner", 
            "lat": 47.6521845, 
            "metroArea": {
                "country": {
                    "displayName": "US"
                }, 
                "state": {
                    "displayName": "WA"
                }, 
                "displayName": "Seattle", 
                "uri": "http://www.songkick.com/metro_areas/2846-us-seattle?utm_source=32233&utm_medium=partner", 
                "id": 2846
            }, 
            "lng": -122.3538836, 
            "id": 11589
        }, 
        "uri": "http://www.songkick.com/concerts/27899154-trout-steak-revival-at-nectar-lounge?utm_source=32233&utm_medium=partner", 
        "start": {
            "date": "2016-11-17", 
            "time": "20:00:00", 
            "datetime": "2016-11-17T20:00:00-0800"
        }, 
        "location": {
            "lat": 47.6521845, 
            "city": "Seattle, WA, US", 
            "lng": -122.3538836
        }, 
        "performance": [
            {
                "artist": {
                    "identifier": [
                        {
                            "mbid": "c84f65ff-dad3-41f3-bbc5-e411d537c909", 
                            "href": "http://api.songkick.com/api/3.0/artists/mbid:c84f65ff-dad3-41f3-bbc5-e411d537c909.json"
                        }
                    ], 
                    "displayName": "Trout Steak Revival", 
                    "uri": "http://www.songkick.com/artists/2923381-trout-steak-revival?utm_source=32233&utm_medium=partner", 
                    "id": 2923381
                }, 
                "displayName": "Trout Steak Revival", 
                "id": 54332369, 
                "billing": "headline", 
                "billingIndex": 1
            }, 
            {
                "artist": {
                    "identifier": [], 
                    "displayName": "The Warren G. Hardings", 
                    "uri": "http://www.songkick.com/artists/3967886-warren-g-hardings?utm_source=32233&utm_medium=partner", 
                    "id": 3967886
                }, 
                "displayName": "The Warren G. Hardings", 
                "id": 54435374, 
                "billing": "support", 
                "billingIndex": 2
            }, 
            {
                "artist": {
                    "identifier": [
                        {
                            "mbid": "527e42d7-ec18-4aaa-9270-102c749f8599", 
                            "href": "http://api.songkick.com/api/3.0/artists/mbid:527e42d7-ec18-4aaa-9270-102c749f8599.json"
                        }
                    ], 
                    "displayName": "The Railsplitters", 
                    "uri": "http://www.songkick.com/artists/5371863-railsplitters?utm_source=32233&utm_medium=partner", 
                    "id": 5371863
                }, 
                "displayName": "The Railsplitters", 
                "id": 54435379, 
                "billing": "support", 
                "billingIndex": 3
            }
        ], 
        "type": "Concert", 
        "id": 27899154
    }, 
    "musicbrainz_response": {
        "type-id": "e431f5f6-b5d2-343d-8b36-72607fffb74b", 
        "name": "Trout Steak Revival", 
        "tags": [], 
        "country": null, 
        "life-span": {
            "ended": false, 
            "begin": "2008", 
            "end": null
        }, 
        "area": {
            "sort-name": "Denver", 
            "disambiguation": "", 
            "name": "Denver", 
            "id": "fc1aee9a-f1a8-45dc-8820-af6b5d7f7450"
        }, 
        "relations": [
            {
                "direction": "forward", 
                "end": null, 
                "target-type": "url", 
                "url": {
                    "resource": "http://www.troutsteak.com/", 
                    "id": "efd79579-a472-41f9-aa43-e051b43c5e6b"
                }, 
                "begin": null, 
                "type-id": "fe33d22f-c3b0-4d68-bd53-a856badf2b15", 
                "ended": false, 
                "source-credit": "", 
                "attributes": [], 
                "type": "official homepage", 
                "target-credit": "", 
                "attribute-values": {}
            }, 
            {
                "direction": "forward", 
                "end": null, 
                "target-type": "url", 
                "url": {
                    "resource": "https://www.facebook.com/TroutSteakRevival", 
                    "id": "75f8ab3e-22d5-4fc8-9307-985e406c30f8"
                }, 
                "begin": null, 
                "type-id": "99429741-f3f6-484b-84f8-23af51991770", 
                "ended": false, 
                "source-credit": "", 
                "attributes": [], 
                "type": "social network", 
                "target-credit": "", 
                "attribute-values": {}
            }
        ], 
        "ipis": [], 
        "end_area": null, 
        "begin_area": {
            "sort-name": "Denver", 
            "disambiguation": "", 
            "name": "Denver", 
            "id": "fc1aee9a-f1a8-45dc-8820-af6b5d7f7450"
        }, 
        "gender-id": null, 
        "gender": null, 
        "sort-name": "Trout Steak Revival", 
        "type": "Group", 
        "id": "c84f65ff-dad3-41f3-bbc5-e411d537c909", 
        "disambiguation": ""
    }, 
    "bandsintown_response": {
        "response": "{\"errors\":[\"Unknown Artist\"]}\n", 
        "error": 404
    }, 
    "ticket_details": {
        "ticket_redirect_url": "https://www.eventbrite.com/e/trout-steak-revival-with-the-warren-g-hardings-and-the-railsplitters-tickets-27261163875?aff=aff0songkick"
    }, 
    "modified_time": 1479442233.0, 
    "created_minutes": 18161, 
    "created_time": 1478566088.0, 
    "modified_minutes": 3559, 
    "id": 27899154
}