{
    "songkick_response": {
        "status": "ok", 
        "popularity": 0.000189, 
        "displayName": "Larry Cordle at Station Inn (November 7, 2016)", 
        "ageRestriction": null, 
        "venue": {
            "displayName": "Station Inn", 
            "uri": "http://www.songkick.com/venues/11063-station-inn?utm_source=32233&utm_medium=partner", 
            "lat": 36.152544, 
            "metroArea": {
                "country": {
                    "displayName": "US"
                }, 
                "state": {
                    "displayName": "TN"
                }, 
                "displayName": "Nashville", 
                "uri": "http://www.songkick.com/metro_areas/11104-us-nashville?utm_source=32233&utm_medium=partner", 
                "id": 11104
            }, 
            "lng": -86.784445, 
            "id": 11063
        }, 
        "uri": "http://www.songkick.com/concerts/27983684-larry-cordle-at-station-inn?utm_source=32233&utm_medium=partner", 
        "start": {
            "date": "2016-11-07", 
            "datetime": "2016-11-07T21:00:00-0600", 
            "time": "21:00:00"
        }, 
        "location": {
            "lat": 36.152544, 
            "city": "Nashville, TN, US", 
            "lng": -86.784445
        }, 
        "performance": [
            {
                "billingIndex": 1, 
                "displayName": "Larry Cordle", 
                "id": 54484234, 
                "billing": "headline", 
                "artist": {
                    "identifier": [
                        {
                            "mbid": "72681b90-031c-4122-9d49-994371ac80a8", 
                            "href": "http://api.songkick.com/api/3.0/artists/mbid:72681b90-031c-4122-9d49-994371ac80a8.json"
                        }
                    ], 
                    "displayName": "Larry Cordle", 
                    "uri": "http://www.songkick.com/artists/452951-larry-cordle?utm_source=32233&utm_medium=partner", 
                    "id": 452951
                }
            }
        ], 
        "type": "Concert", 
        "id": 27983684
    }, 
    "bandsintown_response": {
        "description": "New Monday with Val Storey, Carl Jackson, Larry Cordle & Friends", 
        "title": "Larry Cordle @ The Station Inn in Nashville, TN", 
        "ticket_type": null, 
        "venue": {
            "city": "Nashville", 
            "name": "The Station Inn", 
            "country": "United States", 
            "region": "TN", 
            "longitude": -86.784445, 
            "place": "The Station Inn", 
            "latitude": 36.152544
        }, 
        "facebook_rsvp_url": "http://www.bandsintown.com/event/12844481?app_id=ticketgame&artist=Larry+Cordle&came_from=67", 
        "ticket_url": null, 
        "on_sale_datetime": null, 
        "formatted_datetime": "Monday, November 7, 2016 at 9:00PM", 
        "datetime": "2016-11-07T21:00:00", 
        "formatted_location": "Nashville, TN", 
        "artists": [
            {
                "website": null, 
                "facebook_page_url": "https://www.facebook.com/LarryCordleFan/", 
                "name": "Larry Cordle", 
                "url": "LarryCordle", 
                "tracker_count": 1808, 
                "mbid": "72681b90-031c-4122-9d49-994371ac80a8", 
                "image_url": "https://s3.amazonaws.com/bit-photos/large/7020675.jpeg", 
                "facebook_tour_dates_url": "http://www.bandsintown.com/LarryCordle/facebookapp?came_from=67", 
                "thumb_url": "https://s3.amazonaws.com/bit-photos/thumb/7020675.jpeg"
            }
        ], 
        "ticket_status": "unavailable", 
        "id": 12844481
    }, 
    "musicbrainz_response": {
        "type-id": "b6e035f4-3ce9-331c-97df-83397230b0df", 
        "name": "Larry Cordle", 
        "area": {
            "sort-name": "United States", 
            "disambiguation": "", 
            "iso-3166-1-codes": [
                "US"
            ], 
            "id": "489ce91b-6658-3307-9877-795b68554c98", 
            "name": "United States"
        }, 
        "gender": "Male", 
        "life-span": {
            "ended": false, 
            "begin": "1949-11-16", 
            "end": null
        }, 
        "tags": [
            {
                "count": 1, 
                "name": "bluegrass"
            }, 
            {
                "count": 1, 
                "name": "country"
            }
        ], 
        "relations": [
            {
                "begin": null, 
                "end": null, 
                "target-type": "url", 
                "url": {
                    "resource": "https://www.discogs.com/artist/1088681", 
                    "id": "8eb1b1ff-1d6a-42a0-98a9-2e8359ece3d2"
                }, 
                "direction": "forward", 
                "type-id": "04a5b104-a4c2-4bac-99a1-7b837c37d9e4", 
                "ended": false, 
                "source-credit": "", 
                "attributes": [], 
                "type": "discogs", 
                "target-credit": "", 
                "attribute-values": {}
            }, 
            {
                "direction": "forward", 
                "end": null, 
                "target-type": "url", 
                "url": {
                    "resource": "https://www.wikidata.org/wiki/Q6490125", 
                    "id": "e2877cda-f44f-4434-9cbe-5e9b5596ebe0"
                }, 
                "begin": null, 
                "type-id": "689870a4-a1e4-4912-b17f-7b2664215698", 
                "ended": false, 
                "source-credit": "", 
                "attributes": [], 
                "type": "wikidata", 
                "target-credit": "", 
                "attribute-values": {}
            }, 
            {
                "source-credit": "", 
                "end": null, 
                "target-type": "url", 
                "url": {
                    "resource": "https://en.wikipedia.org/wiki/Larry_Cordle", 
                    "id": "34410053-5472-4351-9f3d-3a28605c8aed"
                }, 
                "direction": "forward", 
                "begin": null, 
                "type-id": "29651736-fa6d-48e4-aadc-a557c6add1cb", 
                "ended": false, 
                "attributes": [], 
                "type": "wikipedia", 
                "target-credit": "", 
                "attribute-values": {}
            }
        ], 
        "ipis": [], 
        "gender-id": "36d3d30a-839d-3eda-8cb3-29be4384e4a9", 
        "end_area": null, 
        "begin_area": null, 
        "sort-name": "Cordle, Larry", 
        "country": "US", 
        "type": "Person", 
        "id": "72681b90-031c-4122-9d49-994371ac80a8", 
        "disambiguation": ""
    }, 
    "id": 27983684, 
    "ticket_details": {
        "ticket_redirect_url": false
    }
}