{
    "url": "http://www.ticketweb.ca/t3/sale/SaleEventDetail?dispatch=loadSelectionData&eventId=6910225", 
    "response_text": {
        "startDate": "2016-12-11T21:00", 
        "performer": [
            {
                "name": "Kool Keith"
            }, 
            {
                "name": "Kosha Dillz"
            }
        ], 
        "name": "Kool Keith, Kosha Dillz", 
        "url": "http://www.ticketweb.com/t3/sale/SaleEventDetail?dispatch=loadSelectionData&eventId=6910225", 
        "offers": [
            {
                "category": "primary", 
                "priceCurrency": "USD", 
                "url": "http://www.ticketweb.com/t3/sale/SaleEventDetail?dispatch=loadSelectionData&eventId=6910225", 
                "price": "17.75", 
                "availability": "InStock", 
                "validFrom": "2016-09-23T10:00", 
                "@type": "Offer"
            }
        ], 
        "location": {
            "sameAs": "http://thebasementnashville.com/", 
            "address": {
                "addressLocality": "Nashville", 
                "addressRegion": "TN", 
                "streetAddress": "917 Woodland St", 
                "postalCode": "37206", 
                "addressCountry": "US"
            }, 
            "@type": "Place", 
            "name": "The Basement East"
        }, 
        "typicalAgeRange": "21+", 
        "@context": "http://schema.org", 
        "doorTime": "20:00", 
        "@type": "MusicEvent"
    }, 
    "response_code": 200
}